atus_transformer/__init__.py
atus_transformer/activityDictionary.py
ATUS_Transformer-1.0.1.dist-info/LICENSE
ATUS_Transformer-1.0.1.dist-info/METADATA
ATUS_Transformer-1.0.1.dist-info/WHEEL
ATUS_Transformer-1.0.1.dist-info/top_level.txt
ATUS_Transformer-1.0.1.dist-info/RECORD
