Metadata-Version: 2.1
Name: ATUS_Transformer
Version: 1.0.1
Summary: A package that transforms activity variables to fewer categories
Home-page: UNKNOWN
Author: Kamila Kolpashnikova
Author-email: kamilakolpashnikova@gmail.com
License: UNKNOWN
Platform: UNKNOWN
Classifier: Programming Language :: Python :: 3
Classifier: License :: OSI Approved :: MIT License
Classifier: Operating System :: OS Independent
Requires-Python: >=3.6
License-File: LICENSE
